new_bot/__init__.py
new_bot/bots.py
new_bot/run.py
new_bot/settings.py
speedapply/__init__.py
speedapply/__main__.py
speedapply/bots.py
speedapply/sites.py
speedapply-0.0.1.dist-info/LICENSE
speedapply-0.0.1.dist-info/METADATA
speedapply-0.0.1.dist-info/WHEEL
speedapply-0.0.1.dist-info/entry_points.txt
speedapply-0.0.1.dist-info/top_level.txt
speedapply-0.0.1.dist-info/RECORD
