Metadata-Version: 2.1
Name: speedapply
Version: 0.0.1
Summary: Package for automatically applying to relevant jobs on popular job boards.
Home-page: https://github.com/benrussell80/speedapply
Author: Ben Russell
Author-email: bprussell80@gmail.com
License: UNKNOWN
Project-URL: Source Code, https://github.com/benrussell80/speedapply
Keywords: job applications
Platform: UNKNOWN
Classifier: Programming Language :: Python :: 3
Classifier: License :: OSI Approved :: MIT License
Requires-Dist: selenium
Requires-Dist: beautifulsoup4
